tf2_data/__init__.py
tf2_data/constants.py
tf2_data/files.py
tf2_data/iecon_items.py
tf2_data/schema.py
tf2_data/schema_items.py
tf2_data/utils.py
tf2_data/json/colors.json
tf2_data/json/defindex_full_names.json
tf2_data/json/defindex_names.json
tf2_data/json/effects.json
tf2_data/json/item_nameids.json
tf2_data/json/killstreaks.json
tf2_data/json/qualities.json
tf2_data/json/schema_items.json
tf2_data/json/schema_overview.json
tf2_data/json/wears.json
tf2_data-1.0.6.dist-info/licenses/LICENSE
tf2_data-1.0.6.dist-info/METADATA
tf2_data-1.0.6.dist-info/WHEEL
tf2_data-1.0.6.dist-info/top_level.txt
tf2_data-1.0.6.dist-info/RECORD
