Metadata-Version: 2.4
Name: tf2-data
Version: 1.0.6
Summary: Item schemas, unusual effects, SKUs and more useful data for TF2 trading
Author-email: offish <overutilization@gmail.com>
Project-URL: Homepage, https://github.com/offish/tf2-data
Project-URL: Bug Tracker, https://github.com/offish/tf2-data/issues
Keywords: tf2,data,sku
Classifier: Programming Language :: Python :: 3
Classifier: License :: OSI Approved :: MIT License
Classifier: Operating System :: OS Independent
Requires-Python: >=3.10
License-File: LICENSE
Requires-Dist: requests
Dynamic: license-file
